binx/__init__.py
binx/adapter.py
binx/collection.py
binx/exceptions.py
binx/registry.py
binx/utils.py
binx-0.4.2.dist-info/LICENSE
binx-0.4.2.dist-info/METADATA
binx-0.4.2.dist-info/WHEEL
binx-0.4.2.dist-info/top_level.txt
binx-0.4.2.dist-info/RECORD
