Metadata-Version: 2.1
Name: binx
Version: 0.4.2
Summary: Interfaces for an in-memory datastore and calc framework using marshmallow + pandas
Home-page: https://github.com/bsnacks000/binx
Author: bsnacks000
Author-email: bsnacks000@gmail.com
License: MIT license
Keywords: binx
Platform: UNKNOWN
Classifier: Development Status :: 5 - Production/Stable
Classifier: Intended Audience :: Developers
Classifier: License :: OSI Approved :: MIT License
Classifier: Natural Language :: English
Classifier: Programming Language :: Python :: 3
Classifier: Programming Language :: Python :: 3.5
Classifier: Programming Language :: Python :: 3.6
Classifier: Programming Language :: Python :: 3.7
Requires-Dist: pandas (>=0.23)
Requires-Dist: marshmallow (>=3)
